LICENSE
MANIFEST.in
README.rst
setup.py
dsq/__init__.py
dsq/cli.py
dsq/compat.py
dsq/http.py
dsq/manager.py
dsq/sched.py
dsq/store.py
dsq/utils.py
dsq/worker.py
dsq/wsgi.py
dsq.egg-info/PKG-INFO
dsq.egg-info/SOURCES.txt
dsq.egg-info/dependency_links.txt
dsq.egg-info/entry_points.txt
dsq.egg-info/not-zip-safe
dsq.egg-info/requires.txt
dsq.egg-info/top_level.txt